[
  {
    "type": "profession",
    "id": "awakened",
    "name": "女惊醒者",
    "description": "你总是很古怪，甚至有点疯狂。但现在，整个世界都疯了，现实正在把自己翻过来，你的思想已经开始觉醒到可怕的真理和黑暗的宇宙奥秘。",
    "points": -1,
    "flags": [
      "SCEN_ONLY"
    ],
    "traits": [
      "AWAKENED",
      "CHEMIMBALANCE"
    ],
    "items": {
      "both": {
        "items": [
          "pants",
          "longshirt",
          "socks",
          "jacket_evac",
          "sneakers",
          "pockknife",
          "water_clean",
          "lighter",
          "wristwatch"
        ],
        "entries": [
          {
            "group": "charged_cell_phone"
          },
          {
            "group": "mental_meds",
            "count": 2
          }
        ]
      },
      "male": [
        "boxer_shorts"
      ],
      "female": [
        "bra",
        "panties"
      ]
    }
  }
]