[
  {
    "id": "grach17_mag",
    "type": "MAGAZINE",
    "name": {
      "str": "Grach 17圆形弹匣"
    },
    "description": "MP-443的弹匣，这个能装17发子弹。",
    "weight": "120 g",
    "volume": "150 ml",
    "price": "80 USD",
    "material": [
      "steel"
    ],
    "symbol": "#",
    "color": "light_gray",
    "looks_like": "8x40_50_mag",
    "ammo_type": "9mm",
    "capacity": 17,
    "flags": [
      "MAG_COMPACT"
    ],
    "pocket_data": [
      {
        "pocket_type": "MAGAZINE",
        "rigid": true,
        "ammo_restriction": {
          "9mm": 17
        }
      }
    ]
  },
  {
    "id": "grach18_mag",
    "type": "MAGAZINE",
    "name": {
      "str": "格拉赫18轮弹匣"
    },
    "description": "MP-443的弹匣，这个可以装18发子弹。",
    "weight": "122 g",
    "volume": "150 ml",
    "price": "85 USD",
    "material": [
      "steel"
    ],
    "symbol": "#",
    "color": "light_gray",
    "looks_like": "8x40_50_mag",
    "ammo_type": "9mm",
    "capacity": 18,
    "flags": [
      "MAG_COMPACT"
    ],
    "pocket_data": [
      {
        "pocket_type": "MAGAZINE",
        "rigid": true,
        "ammo_restriction": {
          "9mm": 18
        }
      }
    ]
  }
]