[
  {
    "id": "mon_zombie_translucent",
    "type": "MONSTER",
    "name": {
      "str": "半透明丧尸"
    },
    "description": "这具狂暴的尸体浑身都是酸液，每走一步都摇摆不定，喷吐着和它身体一样绿的肮脏废渣，淡色的眼睛不知从哪里顺从地凝视着你。",
    "default_faction": "zombie",
    "species": [
      "ZOMBIE",
      "SECROZED_1",
      "HUMAN"
    ],
    "volume": "62500 ml",
    "weight": "81500 g",
    "hp": 70,
    "diff": 1,
    "speed": 100,
    "material": [
      "flesh"
    ],
    "symbol": "⩀",
    "color": "green",
    "aggression": 100,
    "morale": 100,
    "melee_skill": 2,
    "melee_dice": 1,
    "melee_dice_sides": 2,
    "melee_cut": 1,
    "luminance": 2,
    "harvest": "zombie",
    "melee_damage": [
      {
        "damage_type": "acid",
        "amount": 2
      }
    ],
    "armor_bash": 2,
    "armor_cut": 1,
    "armor_fire": 1,
    "special_attacks": [
      [
        "ACID_BARF",
        30
      ]
    ],
    "death_drops": "default_zombie_death_drops",
    "upgrades": {
      "half_life": 14,
      "into": "mon_zombie_pellucid"
    },
    "anger_triggers": [
      "PLAYER_CLOSE"
    ],
    "death_function": {
      "message": "The %s's body leaks acid.",
      "effect": {
        "id": "death_acid",
        "hit_self": true
      }
    },
    "flags": [
      "SEES",
      "HEARS",
      "SMELLS",
      "ACIDPROOF",
      "ACID_BLOOD",
      "STUMBLES",
      "WARM",
      "BASHES",
      "POISON",
      "NO_BREATHE",
      "REVIVES",
      "FILTHY"
    ]
  },
  {
    "id": "mon_zombie_pellucid",
    "type": "MONSTER",
    "name": {
      "str": "透明丧尸"
    },
    "description": "无法辨认的脸上滴着不友好的液体。这只丧尸的皮肤变薄了，使得光线发生了偏移，这可能是由于时间进一步增长而产生的酸反流效应。细看之下，这些纹路主要由浅绿色的光晕组成。",
    "default_faction": "zombie",
    "species": [
      "ZOMBIE",
      "SECROZED_1",
      "HUMAN"
    ],
    "volume": "62500 ml",
    "weight": "81500 g",
    "hp": 90,
    "speed": 100,
    "diff": 5,
    "material": [
      "flesh"
    ],
    "symbol": "⩃",
    "color": "blue_green",
    "aggression": 100,
    "morale": 100,
    "melee_skill": 4,
    "melee_dice": 1,
    "melee_dice_sides": 3,
    "melee_cut": 1,
    "dodge": 1,
    "harvest": "zombie",
    "melee_damage": [
      {
        "damage_type": "acid",
        "amount": 5
      }
    ],
    "luminance": 1,
    "armor_bash": 6,
    "armor_fire": 2,
    "special_attacks": [
      [
        "ACID_BARF",
        30
      ],
      [
        "ACID",
        40
      ],
      {
        "type": "gun",
        "cooldown": 40,
        "move_cost": 150,
        "gun_type": "pellucid_mouth",
        "fake_skills": [
          [
            "gun",
            3
          ],
          [
            "rifle",
            6
          ]
        ],
        "ranges": [
          [
            0,
            8,
            "DEFAULT"
          ]
        ],
        "require_targeting_player": false,
        "require_targeting_npc": false,
        "require_targeting_monster": false,
        "description": "透明的丧尸吐出一团浓缩的酸！"
      }
    ],
    "special_when_hit": [
      "ACIDSPLASH",
      25
    ],
    "death_drops": "default_zombie_death_drops",
    "anger_triggers": [
      "PLAYER_CLOSE"
    ],
    "death_function": {
      "effect": {
        "id": "death_acid",
        "hit_self": true
      },
      "message": "The %s's body leaks acid."
    },
    "flags": [
      "SEES",
      "HEARS",
      "SMELLS",
      "ACIDPROOF",
      "ACID_BLOOD",
      "STUMBLES",
      "WARM",
      "BASHES",
      "POISON",
      "NO_BREATHE",
      "FILTHY",
      "REVIVES"
    ]
  }
]