[
  {
    "id": "792",
    "type": "AMMO",
    "name": {
      "str": "7.92x57 毛瑟尖头弹"
    },
    "description": "7.92×57毫米Mauser是一种无框瓶颈步枪子弹。1903年至1905年，德国帝国采用了7.92×57毫米的毛瑟弹药筒，在两次世界大战中都是德国的军用弹药筒。",
    "weight": "10 g",
    "volume": "250 ml",
    "price": 120,
    "material": [
      "steel",
      "powder"
    ],
    "symbol": "=",
    "color": "dark_gray",
    "count": 30,
    "stack_size": 20,
    "ammo_type": "792",
    "casing": "792_casing",
    "range": 62,
    "damage": {
      "damage_type": "bullet",
      "amount": 30,
      "armor_penetration": 8
    },
    "dispersion": 35,
    "recoil": 200
  },
  {
    "id": "bp_792",
    "copy-from": "792",
    "type": "AMMO",
    "name": {
      "str": "7.92x57 毛瑟尖头弹（黑火药）"
    },
    "proportional": {
      "price": 0.3,
      "damage": {
        "damage_type": "bullet",
        "amount": 0.76,
        "armor_penetration": 0.5
      },
      "recoil": 0.76,
      "dispersion": 1.2
    },
    "extend": {
      "effects": [
        "RECYCLED",
        "BLACKPOWDER",
        "MUZZLE_SMOKE"
      ]
    }
  },
  {
    "type": "GENERIC",
    "id": "792_casing",
    "copy-from": "casing",
    "name": {
      "str": "7.92x57mm 弹壳"
    },
    "description": "7.92x57子弹的空弹壳。",
    "material": [
      "brass"
    ],
    "volume": "25 ml",
    "weight": "1 g"
  }
]