[
  {
    "id": "ceramic_blade_s01",
    "type": "GUNMOD",
    "name": {
      "str": "陶瓷刺刀"
    },
    "description": "一个焊接米长的加固陶瓷刀片为S-01轨道加速器mk2，戳向后像一个反向刺刀，股票应该在那里。刀锋使得发射架无法靠在你的肩膀上。如果你想方设法把火车加速器对准敌人，一定要用这个击中他们。",
    "weight": "3 g",
    "volume": "3 ml",
    "price": "0 cent",
    "install_time": "40 m",
    "cutting": 24,
    "to_hit": -1,
    "qualities": [
      [
        "CUT",
        2
      ],
      [
        "BUTCHER",
        -10
      ],
      [
        "PRY",
        2
      ]
    ],
    "material": [
      "ceramic"
    ],
    "symbol": ":",
    "color": "dark_gray",
    "location": "stock",
    "mod_targets": [
      "rifle"
    ],
    "flags": [
      "IRREMOVABLE"
    ]
  },
  {
    "id": "cushioned_handle_s01",
    "type": "GUNMOD",
    "name": {
      "str": "缓冲手柄"
    },
    "description": "泡沫缓冲处理的S-01铁路加速器mk2安装在皮卡汀尼铁路的地方，景点应该去。它使得把发射器拖在你身边更舒服一点。",
    "weight": "3 g",
    "volume": "3 ml",
    "price": "0 cent",
    "install_time": "20 m",
    "material": [
      "steel",
      "plastic"
    ],
    "symbol": ":",
    "color": "dark_gray",
    "location": "sights",
    "handling_modifier": -1,
    "mod_targets": [
      "rifle"
    ],
    "flags": [
      "IRREMOVABLE"
    ]
  },
  {
    "type": "GUNMOD",
    "id": "accelerator_barrel_s01",
    "name": {
      "str": "调谐磁加速器"
    },
    "dispersion_modifier": -17,
    "to_hit": 2,
    "description": "两块磁化的工业级钢，每一块都用铜线包裹着，用于S-01轨道加速器mk2，作为弹丸的进一步加速器。把手拿开。",
    "location": "barrel",
    "install_time": "0 m",
    "weight": "3 g",
    "color": "light_gray",
    "symbol": ":",
    "material": [
      "steel",
      "copper"
    ],
    "mod_targets": [
      "rifle"
    ],
    "volume": "3 ml",
    "handling_modifier": 2,
    "price": "0 cent",
    "flags": [
      "IRREMOVABLE"
    ]
  },
  {
    "type": "GUNMOD",
    "id": "accelerator_battery",
    "name": {
      "str": "钚电池模组"
    },
    "description": "一个自制的由十根钚棒组成的集束体，用霰弹连接的金属环固定在一起，可以用来降低S-01轨道加速器mk2难以置信的功率消耗。由于它的临时性质，在安全安装到轨道炮外壳之前，它一直在泄漏辐射。",
    "location": "battery",
    "install_time": "25 m",
    "weight": "85 g",
    "color": "green",
    "symbol": ":",
    "material": [
      "steel",
      "plastic"
    ],
    "mod_targets": [
      "rifle"
    ],
    "volume": "250 ml",
    "price": "5000 USD",
    "ups_charges_modifier": -250,
    "flags": [
      "RADIOACTIVE",
      "LEAK_ALWAYS"
    ]
  },
  {
    "type": "GUNMOD",
    "id": "incendiary_battery",
    "name": {
      "str": "燃烧电池模组"
    },
    "description": "一个罐子大小的容器，里面装满了可燃粉末和钚浆，可装填至 S-01 轨道加速器 mk2。如此一来能够将弹丸过热，至于能够点燃沿途但空气，同时大幅提高穿透力。",
    "location": "battery",
    "install_time": "25 m",
    "weight": "85 g",
    "color": "red",
    "symbol": ":",
    "material": [
      "steel",
      "plastic"
    ],
    "mod_targets": [
      "rifle"
    ],
    "volume": "250 ml",
    "price": "5000 USD",
    "ammo_effects": [
      "PLASMA",
      "STREAM_BIG",
      "INCENDIARY"
    ],
    "flags": [
      "RADIOACTIVE"
    ]
  },
  {
    "type": "GUNMOD",
    "id": "shock_battery",
    "name": {
      "str": "冲击电池模组"
    },
    "description": "一个罐子大小的容器，里面装满了镁粉、浓酸和钚浆，可装填至 S-01 轨道加速器 mk2。如此一来能够让弹丸带电，电击被命中的目标。",
    "location": "battery",
    "install_time": "25 m",
    "weight": "85 g",
    "color": "light_blue",
    "symbol": ":",
    "material": [
      "steel",
      "plastic"
    ],
    "mod_targets": [
      "rifle"
    ],
    "volume": "250 ml",
    "price": "5000 USD",
    "ammo_effects": [
      "DRAW_AS_LINE",
      "BOUNCE",
      "LIGHTNING"
    ],
    "flags": [
      "RADIOACTIVE"
    ]
  }
]