[
  {
    "type": "ARMOR",
    "id": "armor_nomad",
    "copy-from": "armor_nomad",
    "name": {
      "str": "游牧连身衣"
    },
    "pocket_data": [
      {
        "max_contains_volume": "21500 ml",
        "max_contains_weight": "1000 kg",
        "max_item_length": "1 km"
      }
    ]
  },
  {
    "type": "ARMOR",
    "id": "armor_scavenger",
    "copy-from": "armor_scavenger",
    "name": {
      "str": "拾荒者套装"
    },
    "pocket_data": [
      {
        "max_contains_volume": "20000 ml",
        "max_contains_weight": "1000 kg",
        "max_item_length": "1 km"
      }
    ]
  },
  {
    "type": "ARMOR",
    "id": "lsurvivor_suit",
    "copy-from": "lsurvivor_suit",
    "name": {
      "str": "幸存者套装（轻型）"
    },
    "pocket_data": [
      {
        "max_contains_volume": "7000 ml",
        "max_contains_weight": "1000 kg",
        "max_item_length": "1 km"
      }
    ]
  },
  {
    "type": "ARMOR",
    "id": "survivor_suit",
    "copy-from": "survivor_suit",
    "name": {
      "str": "幸存者套装"
    },
    "pocket_data": [
      {
        "max_contains_volume": "7000 ml",
        "max_contains_weight": "1000 kg",
        "max_item_length": "1 km"
      }
    ]
  },
  {
    "type": "ARMOR",
    "id": "xlsurvivor_suit",
    "copy-from": "xlsurvivor_suit",
    "name": {
      "str": "幸存者套装（XL）"
    },
    "pocket_data": [
      {
        "max_contains_volume": "8000 ml",
        "max_contains_weight": "1000 kg",
        "max_item_length": "1 km"
      }
    ]
  },
  {
    "type": "ARMOR",
    "id": "wsurvivor_suit",
    "copy-from": "wsurvivor_suit",
    "name": {
      "str": "幸存者套装（防寒）"
    },
    "pocket_data": [
      {
        "max_contains_volume": "5000 ml",
        "max_contains_weight": "1000 kg",
        "max_item_length": "1 km"
      }
    ]
  },
  {
    "type": "ARMOR",
    "id": "h20survivor_suit",
    "copy-from": "h20survivor_suit",
    "name": {
      "str": "幸存者套装（潜水）"
    },
    "pocket_data": [
      {
        "max_contains_volume": "10000 ml",
        "max_contains_weight": "1000 kg",
        "max_item_length": "1 km"
      }
    ]
  }
]